sbx_ocr_correction_viklofg_sweocr/__init__.py
sbx_ocr_correction_viklofg_sweocr/annotations.py
sbx_ocr_correction_viklofg_sweocr/metadata.yaml
sbx_ocr_correction_viklofg_sweocr/ocr_corrector.py
sbx_ocr_correction_viklofg_sweocr/py.typed
sparv_sbx_ocr_correction_viklofg_sweocr-0.5.1.dist-info/METADATA
sparv_sbx_ocr_correction_viklofg_sweocr-0.5.1.dist-info/WHEEL
sparv_sbx_ocr_correction_viklofg_sweocr-0.5.1.dist-info/entry_points.txt
sparv_sbx_ocr_correction_viklofg_sweocr-0.5.1.dist-info/RECORD
