Metadata-Version: 2.3
Name: sparv-sbx-ocr-correction-viklofg-sweocr
Version: 0.5.1
Summary: A sparv plugin for computing suggested OCR improvements.
Project-URL: Homepage, https://spraakbanken.gu.se
Project-URL: Repository, https://github.com/spraakbanken/sparv-sbx-ocr-correction
Project-URL: Bug Tracker, https://github.com/spraakbanken/sparv-sbx-ocr-correction/labels/project%3Aocr-correction-viklofg-sweocr
Author-email: Språkbanken Text <sb-info@svenska.gu.se>, Kristoffer Andersson <kristoffer.andersson@gu.se>
License: MIT
Classifier: Development Status :: 3 - Alpha
Classifier: Intended Audience :: Developers
Classifier: License :: OSI Approved :: MIT License
Classifier: Operating System :: MacOS
Classifier: Operating System :: Microsoft :: Windows
Classifier: Operating System :: POSIX
Classifier: Operating System :: Unix
Classifier: Programming Language :: Python :: 3.9
Classifier: Programming Language :: Python :: 3.10
Classifier: Programming Language :: Python :: 3.11
Classifier: Programming Language :: Python :: 3.12
Classifier: Programming Language :: Python :: Implementation :: CPython
Classifier: Topic :: Utilities
Classifier: Typing :: Typed
Requires-Python: >=3.9
Requires-Dist: parallel-corpus>=0.2.0
Requires-Dist: sparv-pipeline>=5.2.0
Requires-Dist: transformers<4.45.0,>=4.40.0
